grizzlies
